{
  "openapi": "3.0.1",
  "info": {
    "title": "TestTask",
    "version": "1.0"
  },
  "paths": {
    "/api/v1/orders/selected-order": {
      "get": {
        "tags": [
          "Orders"
        ],
        "responses": {
          "200": {
            "description": "Success"
          }
        }
      }
    },
    "/api/v1/orders/selected-orders": {
      "get": {
        "tags": [
          "Orders"
        ],
        "responses": {
          "200": {
            "description": "Success"
          }
        }
      }
    },
    "/api/v1/users/selected-user": {
      "get": {
        "tags": [
          "Users"
        ],
        "responses": {
          "200": {
            "description": "Success"
          }
        }
      }
    },
    "/api/v1/users/selected-users": {
      "get": {
        "tags": [
          "Users"
        ],
        "responses": {
          "200": {
            "description": "Success"
          }
        }
      }
    }
  },
  "components": { }
}